azuredlock.py
role.py
azuredlock-0.0.16.dist-info/DESCRIPTION.rst
azuredlock-0.0.16.dist-info/METADATA
azuredlock-0.0.16.dist-info/RECORD
azuredlock-0.0.16.dist-info/WHEEL
azuredlock-0.0.16.dist-info/entry_points.txt
azuredlock-0.0.16.dist-info/metadata.json
azuredlock-0.0.16.dist-info/top_level.txt
