Metadata-Version: 2.0
Name: azuredlock
Version: 0.0.16
Summary: azure + redlock
Home-page: UNKNOWN
Author: cloudcraeft
Author-email: cloudcraeft@outlook.com
License: MIT
Platform: UNKNOWN
Requires-Python: ~=3.5
Requires-Dist: click
Requires-Dist: requests
